pyreball/__init__.py
pyreball/__main__.py
pyreball/_common.py
pyreball/cfg/config.ini
pyreball/cfg/css.template
pyreball/cfg/external_links.ini
pyreball/cfg/html.template
pyreball/config_generator.py
pyreball/constants.py
pyreball/html.py
pyreball/py.typed
pyreball/text.py
pyreball/utils/__init__.py
pyreball/utils/param.py
pyreball/utils/template.py
pyreball-2.2.1.dist-info/METADATA
pyreball-2.2.1.dist-info/WHEEL
pyreball-2.2.1.dist-info/entry_points.txt
pyreball-2.2.1.dist-info/licenses/LICENSE
pyreball-2.2.1.dist-info/RECORD
