Metadata-Version: 2.4
Name: pyreball
Version: 2.2.1
Summary: Python reporting tool.
License: Apache-2.0
License-File: LICENSE
Keywords: python,reporting,html
Author: Karel Vaculik
Author-email: vaculik.dev@gmail.com
Requires-Python: >=3.8
Classifier: License :: OSI Approved :: Apache Software License
Classifier: Operating System :: OS Independent
Classifier: Programming Language :: Python
Classifier: Programming Language :: Python :: 3
Classifier: Programming Language :: Python :: 3.8
Classifier: Programming Language :: Python :: 3.9
Classifier: Programming Language :: Python :: 3.10
Classifier: Programming Language :: Python :: 3.11
Classifier: Programming Language :: Python :: 3.12
Classifier: Programming Language :: Python :: 3.13
Classifier: Programming Language :: Python :: 3.14
Provides-Extra: examples
Requires-Dist: altair (>=5.0.1,<6.0.0) ; extra == "examples"
Requires-Dist: altair-viewer (>=0.4.0,<0.5.0) ; extra == "examples"
Requires-Dist: bokeh (>=3.1.1,<4.0.0) ; (python_version < "3.9") and (extra == "examples")
Requires-Dist: bokeh (>=3.2.2,<4.0.0) ; (python_version >= "3.12") and (extra == "examples")
Requires-Dist: bokeh (>=3.2.2,<4.0.0) ; (python_version >= "3.9" and python_version < "3.12") and (extra == "examples")
Requires-Dist: matplotlib (>=3.7.2,<4.0.0) ; extra == "examples"
Requires-Dist: numpy (>=1.24.4,<2.0.0) ; (python_version < "3.9") and (extra == "examples")
Requires-Dist: numpy (>=1.25.2,<2.0.0) ; (python_version >= "3.9" and python_version < "3.12") and (extra == "examples")
Requires-Dist: numpy (>=1.26.4,<2.0.0) ; (python_version >= "3.12") and (extra == "examples")
Requires-Dist: pandas (>=2.0.3,<3.0.0) ; (python_version < "3.9") and (extra == "examples")
Requires-Dist: pandas (>=2.0.3,<3.0.0) ; (python_version >= "3.9" and python_version < "3.12") and (extra == "examples")
Requires-Dist: pandas (>=2.2.2,<3.0.0) ; (python_version >= "3.12") and (extra == "examples")
Requires-Dist: plotly (>=5.16.1,<6.0.0) ; extra == "examples"
Requires-Dist: seaborn (>=0.12.2,<0.13.0) ; extra == "examples"
Project-URL: documentation, https://pyreball.readthedocs.io
Project-URL: homepage, https://github.com/karelvaculik/pyreball
